flashmd/__init__.py
flashmd/constraints.py
flashmd/ipi.py
flashmd/models.py
flashmd/stepper.py
flashmd/ase/__init__.py
flashmd/ase/bussi.py
flashmd/ase/langevin.py
flashmd/ase/npt.py
flashmd/ase/velocity_verlet.py
flashmd-0.2.2.dist-info/licenses/LICENSE
flashmd-0.2.2.dist-info/METADATA
flashmd-0.2.2.dist-info/WHEEL
flashmd-0.2.2.dist-info/top_level.txt
flashmd-0.2.2.dist-info/RECORD
