Metadata-Version: 2.4
Name: flashmd
Version: 0.2.2
Summary: Accelerated molecular dynamics with large-time-step predictions
Author: flashmd developers
License: Apache-2.0
Keywords: machine learning,molecular modeling,molecular dynamics
Classifier: Development Status :: 4 - Beta
Classifier: Intended Audience :: Science/Research
Classifier: License :: OSI Approved :: Apache Software License
Classifier: Operating System :: POSIX
Classifier: Operating System :: MacOS :: MacOS X
Classifier: Operating System :: Microsoft :: Windows
Classifier: Programming Language :: Python
Classifier: Programming Language :: Python :: 3
Classifier: Topic :: Scientific/Engineering
Classifier: Topic :: Scientific/Engineering :: Bio-Informatics
Classifier: Topic :: Scientific/Engineering :: Chemistry
Classifier: Topic :: Scientific/Engineering :: Physics
Classifier: Topic :: Software Development :: Libraries
Classifier: Topic :: Software Development :: Libraries :: Python Modules
Requires-Python: >=3.9
License-File: LICENSE
Requires-Dist: metatrain==2025.11
Requires-Dist: ase
Requires-Dist: huggingface_hub
Dynamic: license-file
